[
  {
    "slug": "red-hook",
    "display": "Red Hook",
    "polygon": [
      [
        40.6704,
        -74.018
      ],
      [
        40.6869,
        -74.018
      ],
      [
        40.6869,
        -74.0003
      ],
      [
        40.6704,
        -74.0003
      ]
    ]
  },
  {
    "slug": "carroll-gardens",
    "display": "Carroll Gardens",
    "polygon": [
      [
        40.674,
        -74.0003
      ],
      [
        40.6855,
        -74.0003
      ],
      [
        40.6855,
        -73.991
      ],
      [
        40.674,
        -73.991
      ]
    ]
  },
  {
    "slug": "cobble-hill",
    "display": "Cobble Hill",
    "polygon": [
      [
        40.6855,
        -74.003
      ],
      [
        40.6908,
        -74.003
      ],
      [
        40.6908,
        -73.99
      ],
      [
        40.6855,
        -73.99
      ]
    ]
  },
  {
    "slug": "brooklyn-heights",
    "display": "Brooklyn Heights",
    "polygon": [
      [
        40.6908,
        -74.002
      ],
      [
        40.7035,
        -74.002
      ],
      [
        40.7035,
        -73.991
      ],
      [
        40.6908,
        -73.991
      ]
    ]
  },
  {
    "slug": "dumbo-vinegar-hill",
    "display": "DUMBO & Vinegar Hill",
    "polygon": [
      [
        40.6985,
        -73.992
      ],
      [
        40.706,
        -73.992
      ],
      [
        40.706,
        -73.977
      ],
      [
        40.6985,
        -73.977
      ]
    ]
  },
  {
    "slug": "gowanus",
    "display": "Gowanus",
    "polygon": [
      [
        40.669,
        -73.992
      ],
      [
        40.685,
        -73.992
      ],
      [
        40.685,
        -73.979
      ],
      [
        40.669,
        -73.979
      ]
    ]
  },
  {
    "slug": "park-slope",
    "display": "Park Slope",
    "polygon": [
      [
        40.664,
        -73.9905
      ],
      [
        40.669,
        -73.9905
      ],
      [
        40.6735,
        -73.9855
      ],
      [
        40.676,
        -73.97
      ],
      [
        40.665,
        -73.969
      ]
    ]
  },
  {
    "slug": "williamsburg",
    "display": "Williamsburg",
    "polygon": [
      [
        40.7,
        -73.97
      ],
      [
        40.7235,
        -73.97
      ],
      [
        40.7235,
        -73.934
      ],
      [
        40.7,
        -73.934
      ]
    ]
  },
  {
    "slug": "crown-heights",
    "display": "Crown Heights",
    "polygon": [
      [
        40.6635,
        -73.9645
      ],
      [
        40.6785,
        -73.9645
      ],
      [
        40.6785,
        -73.921
      ],
      [
        40.6635,
        -73.921
      ]
    ]
  },
  {
    "slug": "greenpoint",
    "display": "Greenpoint",
    "polygon": [
      [
        40.7228,
        -73.9615
      ],
      [
        40.739,
        -73.96
      ],
      [
        40.739,
        -73.9505
      ],
      [
        40.7345,
        -73.945
      ],
      [
        40.725,
        -73.941
      ],
      [
        40.7228,
        -73.9425
      ]
    ]
  },
  {
    "slug": "fort-greene",
    "display": "Fort Greene",
    "polygon": [
      [
        40.6835,
        -73.979
      ],
      [
        40.706,
        -73.979
      ],
      [
        40.706,
        -73.966
      ],
      [
        40.6835,
        -73.966
      ]
    ]
  },
  {
    "slug": "sunset-park",
    "display": "Sunset Park",
    "polygon": [
      [
        40.6415,
        -74.029
      ],
      [
        40.665,
        -74.029
      ],
      [
        40.665,
        -73.998
      ],
      [
        40.6415,
        -73.998
      ]
    ]
  },
  {
    "slug": "bay-ridge",
    "display": "Bay Ridge",
    "polygon": [
      [
        40.605,
        -74.043
      ],
      [
        40.6415,
        -74.043
      ],
      [
        40.6415,
        -74.018
      ],
      [
        40.605,
        -74.018
      ]
    ]
  },
  {
    "slug": "downtown-brooklyn",
    "display": "Downtown Brooklyn",
    "polygon": [
      [
        40.6875,
        -73.9925
      ],
      [
        40.701,
        -73.9925
      ],
      [
        40.701,
        -73.9775
      ],
      [
        40.6875,
        -73.9775
      ]
    ]
  },
  {
    "slug": "boerum-hill",
    "display": "Boerum Hill",
    "polygon": [
      [
        40.68,
        -73.9925
      ],
      [
        40.6895,
        -73.9925
      ],
      [
        40.6895,
        -73.979
      ],
      [
        40.68,
        -73.979
      ]
    ]
  },
  {
    "slug": "clinton-hill",
    "display": "Clinton Hill",
    "polygon": [
      [
        40.678,
        -73.968
      ],
      [
        40.701,
        -73.968
      ],
      [
        40.701,
        -73.9525
      ],
      [
        40.678,
        -73.9525
      ]
    ]
  },
  {
    "slug": "prospect-heights",
    "display": "Prospect Heights",
    "polygon": [
      [
        40.6675,
        -73.979
      ],
      [
        40.684,
        -73.979
      ],
      [
        40.684,
        -73.9605
      ],
      [
        40.6675,
        -73.9605
      ]
    ]
  },
  {
    "slug": "bedford-stuyvesant",
    "display": "Bedford-Stuyvesant",
    "polygon": [
      [
        40.676,
        -73.9575
      ],
      [
        40.7,
        -73.9575
      ],
      [
        40.7,
        -73.902
      ],
      [
        40.676,
        -73.902
      ]
    ]
  },
  {
    "slug": "bushwick",
    "display": "Bushwick",
    "polygon": [
      [
        40.69,
        -73.943
      ],
      [
        40.716,
        -73.943
      ],
      [
        40.716,
        -73.8975
      ],
      [
        40.69,
        -73.8975
      ]
    ]
  },
  {
    "slug": "east-new-york",
    "display": "East New York",
    "polygon": [
      [
        40.652,
        -73.905
      ],
      [
        40.7,
        -73.905
      ],
      [
        40.7,
        -73.856
      ],
      [
        40.652,
        -73.856
      ]
    ]
  },
  {
    "slug": "brownsville",
    "display": "Brownsville",
    "polygon": [
      [
        40.654,
        -73.9255
      ],
      [
        40.679,
        -73.9255
      ],
      [
        40.679,
        -73.9
      ],
      [
        40.654,
        -73.9
      ]
    ]
  },
  {
    "slug": "prospect-lefferts-gardens",
    "display": "Prospect Lefferts Gardens",
    "polygon": [
      [
        40.6498,
        -73.9645
      ],
      [
        40.665,
        -73.9645
      ],
      [
        40.665,
        -73.9325
      ],
      [
        40.6498,
        -73.9325
      ]
    ]
  },
  {
    "slug": "east-flatbush",
    "display": "East Flatbush",
    "polygon": [
      [
        40.635,
        -73.9475
      ],
      [
        40.6655,
        -73.9475
      ],
      [
        40.6655,
        -73.9165
      ],
      [
        40.635,
        -73.9165
      ]
    ]
  },
  {
    "slug": "flatbush",
    "display": "Flatbush",
    "polygon": [
      [
        40.632,
        -73.9695
      ],
      [
        40.656,
        -73.9695
      ],
      [
        40.656,
        -73.944
      ],
      [
        40.632,
        -73.944
      ]
    ]
  },
  {
    "slug": "windsor-terrace",
    "display": "Windsor Terrace",
    "polygon": [
      [
        40.6468,
        -73.9855
      ],
      [
        40.6625,
        -73.9855
      ],
      [
        40.6625,
        -73.965
      ],
      [
        40.6468,
        -73.965
      ]
    ]
  },
  {
    "slug": "kensington",
    "display": "Kensington",
    "polygon": [
      [
        40.6335,
        -73.9875
      ],
      [
        40.6495,
        -73.9875
      ],
      [
        40.6495,
        -73.9645
      ],
      [
        40.6335,
        -73.9645
      ]
    ]
  },
  {
    "slug": "greenwood-heights",
    "display": "Greenwood Heights",
    "polygon": [
      [
        40.655,
        -73.9975
      ],
      [
        40.6735,
        -73.9975
      ],
      [
        40.6735,
        -73.9825
      ],
      [
        40.655,
        -73.9825
      ]
    ]
  },
  {
    "slug": "borough-park",
    "display": "Borough Park",
    "polygon": [
      [
        40.623,
        -74.0055
      ],
      [
        40.649,
        -74.0055
      ],
      [
        40.649,
        -73.9845
      ],
      [
        40.623,
        -73.9845
      ]
    ]
  },
  {
    "slug": "dyker-heights",
    "display": "Dyker Heights",
    "polygon": [
      [
        40.6125,
        -74.025
      ],
      [
        40.6475,
        -74.025
      ],
      [
        40.6475,
        -74.0045
      ],
      [
        40.6125,
        -74.0045
      ]
    ]
  }
]